opentracing-stubs/METADATA.toml
opentracing-stubs/__init__.pyi
opentracing-stubs/logs.pyi
opentracing-stubs/propagation.pyi
opentracing-stubs/py.typed
opentracing-stubs/scope.pyi
opentracing-stubs/scope_manager.pyi
opentracing-stubs/span.pyi
opentracing-stubs/tags.pyi
opentracing-stubs/tracer.pyi
opentracing-stubs/ext/__init__.pyi
opentracing-stubs/ext/tags.pyi
opentracing-stubs/harness/__init__.pyi
opentracing-stubs/harness/api_check.pyi
opentracing-stubs/harness/scope_check.pyi
opentracing-stubs/mocktracer/__init__.pyi
opentracing-stubs/mocktracer/binary_propagator.pyi
opentracing-stubs/mocktracer/context.pyi
opentracing-stubs/mocktracer/propagator.pyi
opentracing-stubs/mocktracer/span.pyi
opentracing-stubs/mocktracer/text_propagator.pyi
opentracing-stubs/mocktracer/tracer.pyi
opentracing-stubs/scope_managers/__init__.pyi
opentracing-stubs/scope_managers/asyncio.pyi
opentracing-stubs/scope_managers/constants.pyi
opentracing-stubs/scope_managers/contextvars.pyi
opentracing-stubs/scope_managers/gevent.pyi
opentracing-stubs/scope_managers/tornado.pyi
types_opentracing-2.4.10.20250516.dist-info/licenses/LICENSE
types_opentracing-2.4.10.20250516.dist-info/METADATA
types_opentracing-2.4.10.20250516.dist-info/WHEEL
types_opentracing-2.4.10.20250516.dist-info/top_level.txt
types_opentracing-2.4.10.20250516.dist-info/RECORD
